cursusdb/__init__.py
cursusdb/main.py
cursusdb-1.1.0.dist-info/LICENSE
cursusdb-1.1.0.dist-info/METADATA
cursusdb-1.1.0.dist-info/WHEEL
cursusdb-1.1.0.dist-info/top_level.txt
cursusdb-1.1.0.dist-info/RECORD
