Metadata-Version: 2.1
Name: cursusdb
Version: 1.1.0
Summary: Official CursusDB Native Client for Python
License-File: LICENSE
